antco/__init__.py
antco/aco.py
antco/algorithm.py
antco/ant.py
antco/base.py
antco/c_metrics.cpython-37m-darwin.so
antco/c_ntools.cpython-37m-darwin.so
antco/c_pheromone.cpython-37m-darwin.so
antco/c_policy.cpython-37m-darwin.so
antco/c_utils.cpython-37m-darwin.so
antco/graphics.py
antco/optim.py
antco/pheromone.py
antco/preproc.py
antco/report.py
antco/serialize.py
antco/tools.py
antco/experimental/__init__.py
antco/experimental/experimental.py
antco/hybrid/__init__.py
antco/hybrid/base.py
antco/hybrid/ea.py
antco/hybrid/greedy.py
antco/metaheuristic/__init__.py
antco/metaheuristic/base.py
antco/metaheuristic/ea.py
test/__init__.py
test/ant.py
test/c_metrics.py
test/c_ntools.py
test/c_pheromone.py
test/c_policy.py
test/c_utils.py
test/colony.py
antco-0.1.8.dist-info/LICENSE
antco-0.1.8.dist-info/METADATA
antco-0.1.8.dist-info/WHEEL
antco-0.1.8.dist-info/top_level.txt
antco-0.1.8.dist-info/RECORD
