Metadata-Version: 2.1
Name: antco
Version: 0.1.8
Summary: Ant Colony Optimization framework
Home-page: https://github.com/FernandoGaGu/Ant-Colony-Optimisation/
Author: Fernando García Gutiérrez
Author-email: fegarc05@ucm.es
License: BSD3
Download-URL: https://github.com/FernandoGaGu/Ant-Colony-Optimisation/archive/refs/tags/0.1.tar.gz
Keywords: Optimisation,Ant Colony Optimisation,Metaheuristic,Algorithms
Platform: UNKNOWN
Classifier: Development Status :: 4 - Beta
Classifier: Intended Audience :: Developers
Classifier: Topic :: Software Development :: Build Tools
Classifier: License :: OSI Approved :: BSD License
Classifier: Programming Language :: Python :: 3
Classifier: Programming Language :: Python :: 3.4
Classifier: Programming Language :: Python :: 3.5
Classifier: Programming Language :: Python :: 3.6
Classifier: Programming Language :: Python :: 3.7
Requires-Dist: numpy
Requires-Dist: joblib
Requires-Dist: cython
Requires-Dist: matplotlib
Requires-Dist: deap
Requires-Dist: seaborn
Requires-Dist: networkx
